AMPS.pyd
amps_python_client-5.3.5.1.dist-info/licenses/LICENSE
amps_python_client-5.3.5.1.dist-info/METADATA
amps_python_client-5.3.5.1.dist-info/WHEEL
amps_python_client-5.3.5.1.dist-info/top_level.txt
amps_python_client-5.3.5.1.dist-info/RECORD
