Metadata-Version: 2.4
Name: amps-python-client
Version: 5.3.5.1
Summary: AMPS Python Client
Home-page: https://crankuptheamps.com
Maintainer: 60East Technologies, Incorporated
Maintainer-email: support@crankuptheamps.com
License: Commercial/Proprietary :: see LICENSE
Platform: Linux
Platform: Windows
Classifier: License :: Other/Proprietary License
License-File: LICENSE
Dynamic: classifier
Dynamic: description
Dynamic: description-content-type
Dynamic: home-page
Dynamic: license
Dynamic: license-file
Dynamic: maintainer
Dynamic: maintainer-email
Dynamic: platform
Dynamic: summary
